cli/__init__.py
cli/benchmark.py
cli/cli.py
cli/diagnostic.py
cli/envision.py
cli/run.py
cli/studio.py
cli/waymo.py
cli/zoo.py
envision/__init__.py
envision/client.py
envision/client_config.py
envision/data_formatter.py
envision/etypes.py
envision/server.py
envision/web/__init__.py
envision/web/dist/__init__.py
envision/web/dist/index.html
envision/web/dist/main.js
envision/web/dist/main.js.LICENSE.txt
envision/web/dist/main.js.map
examples/e10_drive/__init__.py
examples/e10_drive/inference/__init__.py
examples/e10_drive/inference/setup.py
examples/e10_drive/inference/contrib_policy/__init__.py
examples/e10_drive/inference/contrib_policy/filter_obs.py
examples/e10_drive/inference/contrib_policy/format_action.py
examples/e10_drive/inference/contrib_policy/frame_stack.py
examples/e10_drive/inference/contrib_policy/make_dict.py
examples/e10_drive/inference/contrib_policy/network.py
examples/e10_drive/inference/contrib_policy/policy.py
examples/e10_drive/train/__init__.py
examples/e10_drive/train/env.py
examples/e10_drive/train/preprocess.py
examples/e10_drive/train/reward.py
examples/e10_drive/train/run.py
examples/e10_drive/train/utils.py
examples/e11_platoon/__init__.py
examples/e11_platoon/inference/__init__.py
examples/e11_platoon/inference/setup.py
examples/e11_platoon/inference/contrib_policy/__init__.py
examples/e11_platoon/inference/contrib_policy/filter_obs.py
examples/e11_platoon/inference/contrib_policy/format_action.py
examples/e11_platoon/inference/contrib_policy/frame_stack.py
examples/e11_platoon/inference/contrib_policy/make_dict.py
examples/e11_platoon/inference/contrib_policy/network.py
examples/e11_platoon/inference/contrib_policy/policy.py
examples/e11_platoon/train/__init__.py
examples/e11_platoon/train/env.py
examples/e11_platoon/train/preprocess.py
examples/e11_platoon/train/reward.py
examples/e11_platoon/train/run.py
examples/e11_platoon/train/utils.py
examples/e12_rllib/__init__.py
examples/e12_rllib/configs.py
smarts-2.0.1.dist-info/LICENSE
smarts-2.0.1.dist-info/METADATA
smarts-2.0.1.dist-info/NOTICE
smarts-2.0.1.dist-info/WHEEL
smarts-2.0.1.dist-info/entry_points.txt
smarts-2.0.1.dist-info/top_level.txt
smarts-2.0.1.dist-info/zip-safe
smarts-2.0.1.dist-info/RECORD
