Metadata-Version: 2.1
Name: smarts
Version: 2.0.1
Summary: UNKNOWN
Home-page: https://github.com/huawei-noah/SMARTS
License: MIT
Platform: UNKNOWN
Classifier: Development Status :: 5 - Production/Stable
Classifier: Programming Language :: Python
Classifier: Programming Language :: Python :: 3 :: Only
Classifier: Programming Language :: Python :: 3.8
Classifier: Programming Language :: Python :: 3.9
Classifier: Programming Language :: Python :: 3.10
Classifier: License :: OSI Approved :: MIT License
Requires-Python: >=3.8
License-File: LICENSE
License-File: NOTICE
Requires-Dist: setuptools (!=50.0,>=41.0.0)
Requires-Dist: click (>=7.1.2)
Requires-Dist: numpy (>=1.19.5)
Requires-Dist: psutil (>=5.4.8)
Requires-Dist: shapely (>=2.0.0)
Requires-Dist: tableprint (>=0.9.1)
Requires-Dist: trimesh (>=3.9.29)
Requires-Dist: scipy
Requires-Dist: yattag (>=1.14.0)
Requires-Dist: PyYAML (>=3.13)
Requires-Dist: twisted (>=21.7.0)
Requires-Dist: pybullet (<4.0,>=3)
Requires-Dist: cloudpickle (>=1.3.0)
Provides-Extra: all
Requires-Dist: av2 (>=0.2.1) ; extra == 'all'
Requires-Dist: Rtree (>=0.9.7) ; extra == 'all'
Requires-Dist: Panda3D (>=1.10.13) ; extra == 'all'
Requires-Dist: panda3d-gltf (==0.13) ; extra == 'all'
Requires-Dist: black[jupyter] (==22.6.0) ; extra == 'all'
Requires-Dist: ipython (<8.13.0,>=7.8.0) ; extra == 'all'
Requires-Dist: grpcio-tools (==1.32.0) ; extra == 'all'
Requires-Dist: isort (==5.7.0) ; extra == 'all'
Requires-Dist: pre-commit (==2.16.0) ; extra == 'all'
Requires-Dist: pylint (>=2.12.2) ; extra == 'all'
Requires-Dist: pytype (==2023.04.18) ; extra == 'all'
Requires-Dist: py-cpuinfo (==9.0.0) ; extra == 'all'
Requires-Dist: mdutils (==1.4.0) ; extra == 'all'
Requires-Dist: matplotlib (>=3.2.2) ; extra == 'all'
Requires-Dist: myst-parser (>=0.18.1) ; extra == 'all'
Requires-Dist: sphinx (>=5.3.0) ; extra == 'all'
Requires-Dist: sphinxcontrib-apidoc (>=0.3.0) ; extra == 'all'
Requires-Dist: sphinxcontrib-spelling (>=8.0.0) ; extra == 'all'
Requires-Dist: sphinx-click (>=4.4.0) ; extra == 'all'
Requires-Dist: sphinx-rtd-theme (>=1.1.1) ; extra == 'all'
Requires-Dist: tornado (>=5.1.1) ; extra == 'all'
Requires-Dist: websocket-client (>=1.2.1) ; extra == 'all'
Requires-Dist: ijson (>=3.1.4) ; extra == 'all'
Requires-Dist: hydra-core ; extra == 'all'
Requires-Dist: gymnasium (>=0.26.3) ; extra == 'all'
Requires-Dist: eclipse-sumo (>=1.12.0) ; extra == 'all'
Requires-Dist: pynput (>=1.7.4) ; extra == 'all'
Requires-Dist: moviepy (==1.0.3) ; extra == 'all'
Requires-Dist: lxml (!=5.0.0) ; extra == 'all'
Requires-Dist: opendrive2lanelet (>=1.2.1) ; extra == 'all'
Requires-Dist: ray (<=2.9.0,>2.4) ; extra == 'all'
Requires-Dist: opencv-python (<5.0,>=4.1.2.30) ; extra == 'all'
Requires-Dist: opencv-python-headless (<5.0,>=4.1.2.30) ; extra == 'all'
Requires-Dist: tensorflow-probability ; extra == 'all'
Requires-Dist: catkin-pkg ; extra == 'all'
Requires-Dist: rospkg ; extra == 'all'
Requires-Dist: pytest (>=6.2.5) ; extra == 'all'
Requires-Dist: pytest-benchmark (>=3.4.1) ; extra == 'all'
Requires-Dist: pytest-cov (>=3.0.0) ; extra == 'all'
Requires-Dist: pytest-xdist (>=2.4.0) ; extra == 'all'
Requires-Dist: pytest-forked (>=1.4.0) ; extra == 'all'
Requires-Dist: ipykernel (>=4.10.1) ; extra == 'all'
Requires-Dist: jupyter-client (>=7.1.2) ; extra == 'all'
Requires-Dist: pytest-notebook (>=0.7.0) ; extra == 'all'
Requires-Dist: torch (>=1.4.0) ; extra == 'all'
Requires-Dist: torchvision (>=0.5.0) ; extra == 'all'
Requires-Dist: tensorflow (>=2.4.0) ; extra == 'all'
Requires-Dist: visdom (>=0.1.8.9) ; extra == 'all'
Requires-Dist: protobuf (<4.0.0,>=3.17.3) ; extra == 'all'
Provides-Extra: argoverse
Requires-Dist: av2 (>=0.2.1) ; extra == 'argoverse'
Requires-Dist: Rtree (>=0.9.7) ; extra == 'argoverse'
Provides-Extra: camera-obs
Requires-Dist: Panda3D (>=1.10.13) ; extra == 'camera-obs'
Requires-Dist: panda3d-gltf (==0.13) ; extra == 'camera-obs'
Provides-Extra: dev
Requires-Dist: black[jupyter] (==22.6.0) ; extra == 'dev'
Requires-Dist: ipython (<8.13.0,>=7.8.0) ; extra == 'dev'
Requires-Dist: grpcio-tools (==1.32.0) ; extra == 'dev'
Requires-Dist: isort (==5.7.0) ; extra == 'dev'
Requires-Dist: pre-commit (==2.16.0) ; extra == 'dev'
Requires-Dist: pylint (>=2.12.2) ; extra == 'dev'
Requires-Dist: pytype (==2023.04.18) ; extra == 'dev'
Provides-Extra: diagnostic
Requires-Dist: py-cpuinfo (==9.0.0) ; extra == 'diagnostic'
Requires-Dist: mdutils (==1.4.0) ; extra == 'diagnostic'
Requires-Dist: matplotlib (>=3.2.2) ; extra == 'diagnostic'
Provides-Extra: doc
Requires-Dist: myst-parser (>=0.18.1) ; extra == 'doc'
Requires-Dist: sphinx (>=5.3.0) ; extra == 'doc'
Requires-Dist: sphinxcontrib-apidoc (>=0.3.0) ; extra == 'doc'
Requires-Dist: sphinxcontrib-spelling (>=8.0.0) ; extra == 'doc'
Requires-Dist: sphinx-click (>=4.4.0) ; extra == 'doc'
Requires-Dist: sphinx-rtd-theme (>=1.1.1) ; extra == 'doc'
Provides-Extra: envision
Requires-Dist: tornado (>=5.1.1) ; extra == 'envision'
Requires-Dist: websocket-client (>=1.2.1) ; extra == 'envision'
Requires-Dist: ijson (>=3.1.4) ; extra == 'envision'
Provides-Extra: examples
Requires-Dist: hydra-core ; extra == 'examples'
Requires-Dist: gymnasium (>=0.26.3) ; extra == 'examples'
Requires-Dist: eclipse-sumo (>=1.12.0) ; extra == 'examples'
Requires-Dist: Rtree (>=0.9.7) ; extra == 'examples'
Provides-Extra: extras
Requires-Dist: pynput (>=1.7.4) ; extra == 'extras'
Provides-Extra: gif-recorder
Requires-Dist: moviepy (==1.0.3) ; extra == 'gif-recorder'
Provides-Extra: gymnasium
Requires-Dist: gymnasium (>=0.26.3) ; extra == 'gymnasium'
Provides-Extra: opendrive
Requires-Dist: lxml (!=5.0.0) ; extra == 'opendrive'
Requires-Dist: opendrive2lanelet (>=1.2.1) ; extra == 'opendrive'
Requires-Dist: Rtree (>=0.9.7) ; extra == 'opendrive'
Provides-Extra: ray
Requires-Dist: ray (<=2.9.0,>2.4) ; extra == 'ray'
Provides-Extra: rllib
Requires-Dist: opencv-python (<5.0,>=4.1.2.30) ; extra == 'rllib'
Requires-Dist: opencv-python-headless (<5.0,>=4.1.2.30) ; extra == 'rllib'
Requires-Dist: ray (<=2.9.0,>2.4) ; extra == 'rllib'
Requires-Dist: tensorflow-probability ; extra == 'rllib'
Provides-Extra: ros
Requires-Dist: catkin-pkg ; extra == 'ros'
Requires-Dist: rospkg ; extra == 'ros'
Provides-Extra: sumo
Requires-Dist: eclipse-sumo (>=1.12.0) ; extra == 'sumo'
Requires-Dist: Rtree (>=0.9.7) ; extra == 'sumo'
Provides-Extra: test
Requires-Dist: pytest (>=6.2.5) ; extra == 'test'
Requires-Dist: pytest-benchmark (>=3.4.1) ; extra == 'test'
Requires-Dist: pytest-cov (>=3.0.0) ; extra == 'test'
Requires-Dist: pytest-xdist (>=2.4.0) ; extra == 'test'
Requires-Dist: pytest-forked (>=1.4.0) ; extra == 'test'
Provides-Extra: test-notebook
Requires-Dist: ipykernel (>=4.10.1) ; extra == 'test-notebook'
Requires-Dist: jupyter-client (>=7.1.2) ; extra == 'test-notebook'
Requires-Dist: pytest-notebook (>=0.7.0) ; extra == 'test-notebook'
Provides-Extra: torch
Requires-Dist: torch (>=1.4.0) ; extra == 'torch'
Requires-Dist: torchvision (>=0.5.0) ; extra == 'torch'
Provides-Extra: train
Requires-Dist: tensorflow (>=2.4.0) ; extra == 'train'
Provides-Extra: visdom
Requires-Dist: visdom (>=0.1.8.9) ; extra == 'visdom'
Provides-Extra: waymo
Requires-Dist: matplotlib (>=3.2.2) ; extra == 'waymo'
Requires-Dist: protobuf (<4.0.0,>=3.17.3) ; extra == 'waymo'
Requires-Dist: Rtree (>=0.9.7) ; extra == 'waymo'
